jupyter_bifrost/__init__.py
jupyter_bifrost/_frontend.py
jupyter_bifrost/_version.py
jupyter_bifrost/bifrost.py
jupyter_bifrost/bifrost_api.py
jupyter_bifrost/bifrost_magic.py
jupyter_bifrost/labextension/package.json
jupyter_bifrost/labextension/static/172.0fe3f5effdc74cebe194.js
jupyter_bifrost/labextension/static/223.06c345a9899216f36c59.js
jupyter_bifrost/labextension/static/270.4fa1be742be40bd35b04.js
jupyter_bifrost/labextension/static/284.e19c41ec51e1b15c2c57.js
jupyter_bifrost/labextension/static/284.e19c41ec51e1b15c2c57.js.LICENSE.txt
jupyter_bifrost/labextension/static/317.fab5f0d4095cf3bc5a79.js
jupyter_bifrost/labextension/static/367.ef7e99fd0e03f120dbf6.js
jupyter_bifrost/labextension/static/396.7d4d081710156350e5c1.js
jupyter_bifrost/labextension/static/423.1e823a1d3d572a0fa09b.js
jupyter_bifrost/labextension/static/437.2a4a6d737d477e806526.js
jupyter_bifrost/labextension/static/456.c4b9d92f592cec2eb583.js
jupyter_bifrost/labextension/static/456.c4b9d92f592cec2eb583.js.LICENSE.txt
jupyter_bifrost/labextension/static/461.c38c2173c4dd491fd08b.js
jupyter_bifrost/labextension/static/461.c38c2173c4dd491fd08b.js.LICENSE.txt
jupyter_bifrost/labextension/static/480.58547c615a3a3ffa9509.js
jupyter_bifrost/labextension/static/502.573b7bab906a875143f4.js
jupyter_bifrost/labextension/static/568.c6e65ab47dea4be5ed8c.js
jupyter_bifrost/labextension/static/581.6f84069b5c93f9e22d7b.js
jupyter_bifrost/labextension/static/683.90f56d7dd2ede7c8ce22.js
jupyter_bifrost/labextension/static/697.7924513910beb67d7dc8.js
jupyter_bifrost/labextension/static/823.5ccd73824f3535ab2285.js
jupyter_bifrost/labextension/static/834.995fcb27e2548f359825.js
jupyter_bifrost/labextension/static/860.1ed4d55347abcd2701ab.js
jupyter_bifrost/labextension/static/877.4d4d38444089ae2c3a07.js
jupyter_bifrost/labextension/static/889.845480fa4937b9b7ed93.js
jupyter_bifrost/labextension/static/990.972e2f945af97c966394.js
jupyter_bifrost/labextension/static/remoteEntry.032870a4757d7c3f36c6.js
jupyter_bifrost-0.3.0.dist-info/LICENSE.txt
jupyter_bifrost-0.3.0.dist-info/METADATA
jupyter_bifrost-0.3.0.dist-info/WHEEL
jupyter_bifrost-0.3.0.dist-info/top_level.txt
jupyter_bifrost-0.3.0.dist-info/RECORD
